iatoolkit/__init__.py
iatoolkit/base_company.py
iatoolkit/company_registry.py
iatoolkit/iatoolkit.py
services/__init__.py
services/api_service.py
services/benchmark_service.py
services/dispatcher_service.py
services/document_service.py
services/excel_service.py
services/file_processor_service.py
services/history_service.py
services/jwt_service.py
services/load_documents_service.py
services/mail_service.py
services/profile_service.py
services/prompt_manager_service.py
services/query_service.py
services/search_service.py
services/sql_service.py
services/tasks_service.py
services/user_feedback_service.py
services/user_session_context_service.py
iatoolkit_core-0.3.0.dist-info/METADATA
iatoolkit_core-0.3.0.dist-info/WHEEL
iatoolkit_core-0.3.0.dist-info/top_level.txt
iatoolkit_core-0.3.0.dist-info/RECORD
